README.md
setup.py
databricks_utils/__init__.py
databricks_utils/aws.py
databricks_utils/vega.py
databricks_utils.egg-info/PKG-INFO
databricks_utils.egg-info/SOURCES.txt
databricks_utils.egg-info/dependency_links.txt
databricks_utils.egg-info/top_level.txt