Metadata-Version: 2.1
Name: databricks-utils
Version: 0.0.7
Summary: Ease-of-use utility tools for databricks notebooks.
Home-page: https://github.com/e2fyi/databricks-utils
Author: William Teo
Author-email: eterna2@hotmail.com
License: Apache License 2.0
Platform: UNKNOWN
